README.md
setup.py
m_formatter_logging.egg-info/PKG-INFO
m_formatter_logging.egg-info/SOURCES.txt
m_formatter_logging.egg-info/dependency_links.txt
m_formatter_logging.egg-info/requires.txt
m_formatter_logging.egg-info/top_level.txt
mobio/libs/logging/__init__.py
mobio/libs/logging/logging.conf