Metadata-Version: 2.1
Name: m-formatter-logging
Version: 1.0.5
Summary: MobioLogging
Home-page: UNKNOWN
Author: MOBIO
Author-email: contact@mobio.io
License: UNKNOWN
Platform: UNKNOWN
Requires-Python: >=3.8
